simple_math_toolkit/__init__.py
simple_math_toolkit/algebra.py
simple_math_toolkit/arithmetic.py
simple_math_toolkit/geometry.py
simple_math_toolkit/stats.py
simple_math_toolkit-0.1.2.dist-info/licenses/LICENSE
simple_math_toolkit-0.1.2.dist-info/METADATA
simple_math_toolkit-0.1.2.dist-info/WHEEL
simple_math_toolkit-0.1.2.dist-info/top_level.txt
simple_math_toolkit-0.1.2.dist-info/RECORD
