Metadata-Version: 2.4
Name: simple-math-toolkit
Version: 0.1.2
Summary: A tiny, multi-module math toolkit with basic arithmetic, algebra, stats, and geometry (library-only).
Author-email: Iurii Vakaliuk <iurii.vakaliuk@tu-dresden.de>
License-Expression: MIT
Classifier: Programming Language :: Python :: 3
Classifier: Programming Language :: Python :: 3 :: Only
Classifier: Operating System :: OS Independent
Classifier: Topic :: Scientific/Engineering :: Mathematics
Requires-Python: >=3.9
License-File: LICENSE
Dynamic: license-file
